cbinsigths/CBInsights.py
cbinsigths/__init__.py
cbinsigths/utils.py
cbinsights_scraper-0.1.0.dist-info/METADATA
cbinsights_scraper-0.1.0.dist-info/WHEEL
cbinsights_scraper-0.1.0.dist-info/top_level.txt
cbinsights_scraper-0.1.0.dist-info/RECORD
