Metadata-Version: 2.1
Name: cbinsights-scraper
Version: 0.1.0
Summary: This project is a scraper for CB Insights, designed to gather information on companies using the public API and web scraping. It provides functionalities to search for companies by name and obtain detailed information about a specific company, including logo, website, description, specifications, news, FAQs, competitors, and address.
Home-page: https://github.com/Diego-Arrechea/CBInsights-scraper
Author: Diego Arrechea
Author-email: diego.arrechea.job@gmail.com
License: MIT
Requires-Python: >=3.6
Requires-Dist: requests
Requires-Dist: beautifulsoup4
